{
  "active_students_comp": [
    { "username": "KingBeckerle#5724", "id": "589648586325753867" },
    { "username": "kliqz_", "id": "230164372155138049" },
    { "username": "murtair", "id": "424375299082420224" },
    { "username": "sparky_engineer", "id": "697867587077275709" },
    { "username": "comptv", "id": "218459064701681674" },
    { "username": "im_micro", "id": "377953652750417920" },
    { "username": "watubi", "id": "208394361661161472" },
    { "username": "GKnirks#9673", "id": "609203192915558440" },
    { "username": "zula6752", "id": "777012111259860994" },
    { "username": "kameren.", "id": "688975967141756985" },
    { "username": "stryder94.", "id": "388804532253229057" },
    { "username": "wishwasbetter", "id": "911652847496605737" },
    { "username": "friendlyfennec", "id": "106414345675632640" },
    { "username": "knearble", "id": "868683826107383840" },
    { "username": "fatalmistake830", "id": "1114969267381751939" },
    { "username": "saltysourboy#6921", "id": "942328976381202472" },
    { "username": "calbrenar", "id": "216991059543195649" },
    { "username": "xpsychoxc", "id": "694949793092468816" },
    { "username": "mutterz", "id": "158760710430523392" },
    { "username": "thiccsalsa", "id": "382377191784185858" },
    { "username": "kenjinara", "id": "150418831213330433" },
    { "username": "uknpoopie", "id": "787066158519287838" },
    { "username": "Deadly#3865", "id": "366675135291195394" },
    { "username": "michelangelo001", "id": "423601897384050690" },
    { "username": "jay.lew", "id": "257684741216665600" },
    { "username": "joswifty", "id": "903834029118337064" },
    { "username": "Linkerdoodle#2302", "id": "380176840448278530" },
    { "username": "grimprophit", "id": "139031262017880064" },
    { "username": "zen_ven", "id": "873924416315203594" },
    { "username": "l3bthunder", "id": "236284455415709696" },
    { "username": "night_ian", "id": "937035368509874216" },
    { "username": "bramboz03", "id": "376482824284536833" },
    { "username": "Drunkenheadshot#4158", "id": "159552970847944704" },
    { "username": "zorkblat", "id": "558379833718210561" },
    { "username": "z8.", "id": "109969533418090496" },
    { "username": "gamehawkrl", "id": "587068514486059009" },
    { "username": "irishwhips", "id": "468956440195891201" },
    { "username": "axo0899", "id": "539519755539972107" },
    { "username": "leoredin", "id": "212017548269453316" },
    { "username": "kdizzle909", "id": "109493389740761088" },
    { "username": "jayelevate", "id": "192413521894572033" },
    { "username": "xxbalockadudexx", "id": "937287976436760596" },
    { "username": "esvino", "id": "215937257557852162" },
    { "username": "axelitoooooo", "id": "737836091188445314" },
    { "username": "len6174", "id": "346061702481182721" },
    { "username": "tyler3990", "id": "384161344020021248" },
    { "username": "ryanblok8", "id": "635088263564230656" },
    { "username": "nogwito", "id": "913201334067535872" },
    { "username": "myguy6036", "id": "340586614067560449" }
  ],
  "active_students_nytro": [
    { "username": "ironchungis", "id": "505892230511460353" },
    { "username": "bizarlo", "id": "623469672393867275" },
    { "username": "daydarkness_", "id": "109801691620077568" },
    { "username": ".arcanist", "id": "168565043519160321" },
    { "username": "tercool", "id": "355216357664620545" },
    { "username": "stank94", "id": "529861955121577984" },
    { "username": "noodlegod11", "id": "141547287292674048" },
    { "username": "boozrboonior", "id": "326417075222478848" },
    { "username": "FelixTheCat#2561", "id": "229774433420705792" },
    { "username": "nsd_glizzy", "id": "165994764141985792" },
    { "username": "metal99", "id": "1130026107253571734" },
    { "username": "aladind", "id": "281915903371640832" },
    { "username": "firerysc", "id": "728700786057543780" },
    { "username": "mrflawlessjazz", "id": "295206383266037760" },
    { "username": "voopool", "id": "612828132042604544" },
    { "username": "gritch8181", "id": "794061715582484511" },
    { "username": "lumitysomers", "id": "281998613729509376" },
    { "username": "scout_xc", "id": "938471666768547904" },
    { "username": "paasol", "id": "206289970028085249" },
    { "username": "wrenomega", "id": "155380995992977410" },
    { "username": "dsgotthatdope", "id": "753001855449170072" },
    { "username": "ornskry", "id": "216342956829966357" },
    { "username": "dubchitts", "id": "556543475387072522" },
    { "username": "breslin.", "id": "205523410468470784" },
    { "username": "bjorkie", "id": "217829100650364938" },
    { "username": "shadowfahrer", "id": "1111757510928502836" },
    { "username": "twily907", "id": "288808810049437708" },
    { "username": "benny4133", "id": "702008989273161818" },
    { "username": "awesomninjadude", "id": "213164797775052801" },
    { "username": "devilfang99", "id": "455064450773417994" },
    { "username": "iseverwitt", "id": "1079860595681144832" },
    { "username": "chance2oo", "id": "1101209006204272702" },
    { "username": "robmavo", "id": "291294032343203841" },
    { "username": "jimmyg_exp", "id": "701616940975784037" },
    { "username": "ehitztonns", "id": "620023174742147097" },
    { "username": "gv425", "id": "426982482064310292" }
  ],
  "active_students_shoebill": [
    { "username": "gurumorro", "id": "316814469365891073" },
    { "username": "_th8", "id": "433512290390638593" },
    { "username": "xzoarny", "id": "310787508193722370" },
    { "username": "speed_demon1215", "id": "313917119593054209" },
    { "username": "jbenden97", "id": "677953860647780393" },
    { "username": "Qredibilty#0461", "id": "745991073574420562" },
    { "username": "smallkitten452", "id": "589909096459665427" },
    { "username": "thesoulreaper77", "id": "346128742164463620" },
    { "username": "towfart", "id": "311330882549972992" },
    { "username": "smashboarder360", "id": "227517973068382208" },
    { "username": "mauribuho", "id": "680209269177450669" },
    { "username": "bas.z", "id": "330382958982856704" },
    { "username": "captaindizzward", "id": "715355155834601554" },
    { "username": "brokenhumortv", "id": "497525302906322964" },
    { "username": "aeiou_.", "id": "121988443138949121" },
    { "username": "savageinwa206", "id": "371530684604612609" },
    { "username": "platypus752", "id": "886900472672321557" },
    { "username": "honestjoe22", "id": "439010168085413889" },
    { "username": "riceputting", "id": "442183374384267264" },
    { "username": "squarebodysky", "id": "221117228593053697" },
    { "username": "mrgeneralq", "id": "663176278400172081" },
    { "username": "ph3s", "id": "279427337873784833" },
    { "username": "bigbapps", "id": "672012414409113611" },
    { "username": "fastmadcow", "id": "219266373778407426" },
    { "username": "fnbvex", "id": "422916557174472704" },
    { "username": "warrenonamission", "id": "1146138851413331968" },
    { "username": "itwasmoose", "id": "757830157020168253" },
    { "username": "amadeus6949", "id": "208024858313883648" },
    { "username": "muffy95", "id": "271971523919609877" },
    { "username": "deadguy4533", "id": "759139323747762176" },
    { "username": "acespade1551", "id": "470801440567459852" },
    { "username": "lightbringer4", "id": "881625081044934717" },
    { "username": "anti47", "id": "252038910870421505" },
    { "username": "trinitykiller", "id": "362782576211001344" },
    { "username": "coltswill07", "id": "698589655372660756" },
    { "username": "qfoal", "id": "539900045579911188" },
    { "username": "heroicevil", "id": "205076790752968704" },
    { "username": "le.frenchfry82#8890", "id": "351899556767858698" },
    { "username": ".miroo.", "id": "757310061797179462" },
    { "username": "piquitodulce", "id": "180445684816805888" },
    { "username": "TheShinyOreo#5588", "id": "267809988863459329" },
    { "username": "dtrain4095", "id": "293925724945907713" },
    { "username": "stupidshoebill", "id": "487244757312077834" },
    { "username": "gerdian", "id": "254479794840928256" },
    { "username": "kairo631", "id": "345402438687391744" },
    { "username": "olympicdmdiver", "id": "488649715903102977" },
    { "username": "poonjamtheman", "id": "493900685612679179" },
    { "username": "labxflamingo", "id": "316064302798995467" }
  ],
  "active_students_puf": [
    { "username": "schmidtl14.", "id": "330993318643105792" },
    { "username": "poopman1571", "id": "773020372714389544" },
    { "username": "averagezeus", "id": "975861180923006996" },
    { "username": "adrien2000d", "id": "321484356243685376" },
    { "username": "art3myss", "id": "149513025060208640" },
    { "username": "bndostreams", "id": "882084683930816522" },
    { "username": "alienlaser", "id": "570063026561220608" },
    { "username": "scotttromp", "id": "346842272505135104" },
    { "username": "tussle_rox", "id": "267765466146013184" },
    { "username": "preet21", "id": "1064442948915302481" },
    { "username": "chadly0505", "id": "748976458830971041" },
    { "username": "sweetjamesjones", "id": "313105870126841856" },
    { "username": "mitch1333", "id": "683797730937667714" },
    { "username": "flowinghot", "id": "175275562758045696" },
    { "username": "gtrjosh", "id": "734743875096150108" },
    { "username": "backstube.", "id": "580813434082426889" },
    { "username": "boog4894", "id": "630556027301003284" },
    { "username": "shkronkle", "id": "340334375059193857" },
    { "username": "gabetrix08", "id": "645433688779390976" },
    { "username": "ruffini48", "id": "946855462106710037" },
    { "username": "filthyca5ual", "id": "336309321228877825" },
    { "username": "baloothesavant", "id": "1103062757491880017" },
    { "username": "tsholey1#4568", "id": "1035581722860986488" },
    { "username": "XTJDSX99#7259", "id": "929266743199805450" },
    { "username": "dippins_", "id": "271445263007219715" },
    { "username": ".dosfx", "id": "1042792342161215520" },
    { "username": "rewdcg", "id": "885579639806898207" },
    { "username": "blade.runner_", "id": "617833370738491443" },
    { "username": "ainkern", "id": "451175374190280714" },
    { "username": "tutti077", "id": "427586113503363093" },
    { "username": "mentioned", "id": "352660822725754883" },
    { "username": "gschell", "id": "759149915691024484" },
    { "username": "str1k3r55", "id": "322657564166848513" },
    { "username": "kal3idos", "id": "198389235676348416" },
    { "username": "gowkula", "id": "395271809001455618" },
    { "username": ".neurro", "id": "211909148575662080" },
    { "username": "csh10", "id": "376572039382695938" },
    { "username": "jcub7264", "id": "1024547253874081792" },
    { "username": "fanaticdlt", "id": "216002925468581899" },
    { "username": "kengia", "id": "276095823899787266" },
    { "username": "thechronicpain", "id": "821169098724605972" },
    { "username": "vgunnarr", "id": "472202805348794368" },
    { "username": "willowette", "id": "390689555063504896" },
    { "username": "nmtotra", "id": "208070363979055106" },
    { "username": "viciousmagician", "id": "430688352858013697" },
    { "username": "imtoxicch", "id": "452586809785057290" }
  ],
  "active_students_curtis": [
    { "username": "kidsen97", "id": "315177236204486657" },
    { "username": "dragonking8180", "id": "677718645857714187" },
    { "username": "xflikrlz", "id": "527011831508762647" },
    { "username": "bredskiii", "id": "699953055873106020" },
    { "username": "right_twix.", "id": "1085684261459341312" },
    { "username": "drew45697", "id": "492203736517705749" },
    { "username": "dagaspack", "id": "388421778428657665" },
    { "username": "luesasole", "id": "829110363395457076" },
    { "username": "arnaud8048", "id": "399500290908356608" },
    { "username": "x.crab.x", "id": "368221987518152717" },
    { "username": "viorise", "id": "359026729500803082" },
    { "username": "dray7896", "id": "642811885753991188" },
    { "username": "mohammedza", "id": "976581180054970389" },
    { "username": "afghandannn", "id": "926971915845898290" },
    { "username": "thun.", "id": "350326199706451968" },
    { "username": "kitkait_", "id": "485621301017313291" },
    { "username": "shadowstalkerxyz", "id": "776131952843423764" },
    { "username": "griassdiservas", "id": "759061796438409256" },
    { "username": "bro.ro711", "id": "734081035834359810" },
    { "username": "toustii", "id": "275399540696416257" },
    { "username": "extraordinarilyhumble", "id": "1053499017998377012" },
    { "username": "Synna#4928", "id": "158637870750367744" },
    { "username": "fuzzyun1c0rn", "id": "656050458670006274" }
  ]
}
